usefuladbasyncio/README.MD
usefuladbasyncio/__init__.py
usefuladbasyncio/requirements.txt
usefuladbasyncio/thirdparty.json
usefuladbasyncio-0.10.dist-info/LICENSE.rst
usefuladbasyncio-0.10.dist-info/METADATA
usefuladbasyncio-0.10.dist-info/WHEEL
usefuladbasyncio-0.10.dist-info/top_level.txt
usefuladbasyncio-0.10.dist-info/RECORD
