Metadata-Version: 2.1
Name: usefuladbasyncio
Version: 0.10
Summary: asyncio version of usefuladb
Home-page: https://github.com/hansalemaos/usefuladbasyncio
Author: Johannes Fischer
Author-email: aulasparticularesdealemaosp@gmail.com
License: MIT
Keywords: android,adb
Classifier: Development Status :: 4 - Beta
Classifier: Programming Language :: Python :: 3 :: Only
Classifier: Programming Language :: Python :: 3.10
Classifier: Topic :: Software Development :: Libraries :: Python Modules
Classifier: Topic :: Utilities
License-File: LICENSE.rst
Requires-Dist: kthread
Requires-Dist: usefuladb
